{
  "tool_name": "Bash",
  "tool_input_preview": "{\"command\":\"cd /home/mareox/GIT/homelab-journal/panos-pytest-baseline && PANOS_FIXTURE_DIR=examples/fixtures uv run pytest tests/ -v 2>&1\",\"timeout\":60000,\"description\":\"Re-run pytest after fixing xpa...",
  "error": "Exit code 1\n============================= test session starts ==============================\nplatform linux -- Python 3.13.12, pytest-9.0.3, pluggy-1.6.0 -- /home/mareox/GIT/homelab-journal/panos-pytest-baseline/.venv/bin/python\ncachedir: .pytest_cache\nrootdir: /home/mareox/GIT/homelab-journal/panos-pytest-baseline\nconfigfile: pyproject.toml\ncollecting ... collected 14 items\n\ntests/test_baseline.py::test_firewall_reachable PASSED                   [  7%]\ntests/test_baseline.py::test_panos_versio...",
  "timestamp": "2026-05-02T09:53:52.963Z",
  "retry_count": 4
}